scrapy_kk_plus/__init__.py
scrapy_kk_plus/__version__.py
scrapy_kk_plus/middlewares.py
scrapy_kk_plus/pipelines.py
scrapy_kk_plus/libs/__init__.py
scrapy_kk_plus/libs/bloomfilter.py
scrapy_kk_plus/libs/defaults.py
scrapy_kk_plus/libs/dupefilter.py
scrapy_kk_plus/libs/pipelinesbase.py
scrapy_kk_plus/libs/scheduler.py
scrapy_kk_plus/use/PermanentFilterManager.py
scrapy_kk_plus/use/__init__.py
Scrapy_kk_Plus-0.1.4.dist-info/METADATA
Scrapy_kk_Plus-0.1.4.dist-info/WHEEL
Scrapy_kk_Plus-0.1.4.dist-info/top_level.txt
Scrapy_kk_Plus-0.1.4.dist-info/RECORD
