Metadata-Version: 2.1
Name: Scrapy-kk-Plus
Version: 0.1.4
Summary: Plus Support for Scrapy
Home-page: https://github.com/xxx
Author: gchristencen46
Author-email: gchristencen46@gmail.com
License: MIT
Platform: UNKNOWN
Classifier: License :: OSI Approved :: MIT License
Classifier: Programming Language :: Python :: 3.5
Classifier: Programming Language :: Python :: 3.6
Classifier: Programming Language :: Python :: 3.7
Classifier: Programming Language :: Python :: 3.8
Classifier: Programming Language :: Python :: Implementation :: CPython
Classifier: Programming Language :: Python :: Implementation :: PyPy
Requires-Python: >=3.5.0
Requires-Dist: PyMySQL (~=1.0.2)
Requires-Dist: Scrapy (~=1.8.0)
Requires-Dist: Twisted (~=21.7.0)
Requires-Dist: redis (~=3.5.3)
Requires-Dist: scrapy-redis (>=0.6.8)
Requires-Dist: setuptools (~=59.2.0)
